bb_openpyxl/__init__.py
bb_openpyxl/_formula.py
bb_openpyxl/_insert.py
bb_openpyxl/_range.py
bb_openpyxl/_utils.py
bb_openpyxl/delete.py
bb_openpyxl/insert.py
bb_openpyxl/sort.py
bb_openpyxl/tests/__init__.py
bb_openpyxl/tests/delete_test.py
bb_openpyxl/tests/formula_test.py
bb_openpyxl/tests/insert_test.py
bb_openpyxl/tests/sort_test.py
bb_openpyxl-0.2.2.dist-info/LICENSE
bb_openpyxl-0.2.2.dist-info/METADATA
bb_openpyxl-0.2.2.dist-info/WHEEL
bb_openpyxl-0.2.2.dist-info/top_level.txt
bb_openpyxl-0.2.2.dist-info/RECORD
